evotrain/__init__.py
evotrain/_version.py
evotrain/config.py
evotrain/geotiff.py
evotrain/job_submit.sh
evotrain/labels.py
evotrain/meteo.py
evotrain/reader.py
evotrain/stats.py
evotrain/models/__init__.py
evotrain/models/callbacks.py
evotrain/models/evonet.py
evotrain/models/transforms.py
evotrain/models/lcm/__init__.py
evotrain/models/lcm/base/arch.py
evotrain/models/lcm/base/callbacks.py
evotrain/models/lcm/base/config.py
evotrain/models/lcm/base/dataset.py
evotrain/models/lcm/base/inference.py
evotrain/models/lcm/base/model.py
evotrain/models/lcm/base/trainer.py
evotrain/models/lcm/roads/__init__.py
evotrain/models/lcm/roads/arch.py
evotrain/models/lcm/roads/callbacks.py
evotrain/models/lcm/roads/dataset.py
evotrain/models/lcm/roads/inference.py
evotrain/models/lcm/roads/model.py
evotrain/models/lcm/roads/scaling.py
evotrain/models/lcm/roads/trainer.py
evotrain/models/lcm10/__init__.py
evotrain/models/lcm10/v10/__change_masks_meta.ipynb
evotrain/models/lcm10/v10/__inference.ipynb
evotrain/models/lcm10/v10/__init__.py
evotrain/models/lcm10/v10/__train_dataset_test.ipynb
evotrain/models/lcm10/v10/__train_model_dev.ipynb
evotrain/models/lcm10/v10/_batch_train.sh
evotrain/models/lcm10/v10/_copy_model.sh
evotrain/models/lcm10/v10/_train.sh
evotrain/models/lcm10/v10/_train_template.sh
evotrain/models/lcm10/v10/arch.py
evotrain/models/lcm10/v10/callbacks.py
evotrain/models/lcm10/v10/config.py
evotrain/models/lcm10/v10/dataset.py
evotrain/models/lcm10/v10/inference.py
evotrain/models/lcm10/v10/model.py
evotrain/models/lcm10/v10/trainer.py
evotrain/models/lcm10/v10/trainer.py.save
evotrain/models/lcm10/v10/debug_models/base_mep_debug/version_0/hparams.yaml
evotrain/models/lcm10/v10/debug_models/base_mep_debug/version_1/hparams.yaml
evotrain/models/lcm10/v10/debug_models/base_mep_debug/version_2/hparams.yaml
evotrain/models/lcm10/v10/debug_models/base_mep_debug/version_3/hparams.yaml
evotrain/models/lcm10/v11/__change_masks_meta.ipynb
evotrain-0.0.18.dist-info/METADATA
evotrain-0.0.18.dist-info/WHEEL
evotrain-0.0.18.dist-info/licenses/LICENSE
evotrain-0.0.18.dist-info/RECORD
