Metadata-Version: 2.4
Name: evotrain
Version: 0.0.18
Summary: Evoland training workflows
Author: Daniele Zanaga, Wanda De Keersmaecker, Yannis Kalfas
License-File: LICENSE
Classifier: Operating System :: OS Independent
Classifier: Programming Language :: Python :: 3
Requires-Python: <=3.12,>=3.11
Requires-Dist: climatic-regions>=0.0.4
Requires-Dist: fastparquet>=2024.2.0
Requires-Dist: joblib>=1.4.2
Requires-Dist: lightning>=2.3.3
Requires-Dist: loguru==0.7.2
Requires-Dist: matplotlib>=3.7.5
Requires-Dist: numpy<2.0.0
Requires-Dist: pyarrow>=17.0.0
Requires-Dist: pydantic>=2.10.6
Requires-Dist: rasterio>=1.2.10
Requires-Dist: rio-tiler>=7.2.2
Requires-Dist: satio-pc>=0.0.9
Requires-Dist: segmentation-models-pytorch>=0.3.3
Requires-Dist: tensorboard>=2.14.0
Requires-Dist: torch>=2.5.0
Requires-Dist: torchvision>=0.20.0
Requires-Dist: veg-workflows==0.2.0
Requires-Dist: xarray>=1.2.10
Provides-Extra: extra
Requires-Dist: deepdiff>=8.3.0; extra == 'extra'
Requires-Dist: ipython; extra == 'extra'
Requires-Dist: rich>=13.9.4; extra == 'extra'
